teamhack_db/__init__.py
teamhack_db/__main__.py
teamhack_db/cli.py
teamhack_db/conf.py
teamhack_db/sql.py
teamhack_db/util.py
teamhack_db-0.0.732.dist-info/METADATA
teamhack_db-0.0.732.dist-info/WHEEL
teamhack_db-0.0.732.dist-info/top_level.txt
teamhack_db-0.0.732.dist-info/RECORD
