Metadata-Version: 2.1
Name: teamhack-db
Version: 0.0.732
Summary: Hack the Box Team Support Services
Requires-Dist: dnslib
Requires-Dist: psycopg2
Provides-Extra: rel
Requires-Dist: twine ; extra == 'rel'
Provides-Extra: test
Requires-Dist: coverage ; extra == 'test'
Requires-Dist: dnslib ; extra == 'test'
Requires-Dist: pytest ; extra == 'test'
